{
    "logo": {
        "altText": "vhjvv",
        "styles": {
            "self": {
                "margin": [
                    "mr-0",
                    "mt-0",
                    "ml-0",
                    "mb-0"
                ],
                "padding": [
                    "pl-0",
                    "pt-0",
                    "pr-0",
                    "pb-0"
                ],
                "borderRadius": "xx-small",
                "borderColor": "border-dark",
                "borderWidth": 1,
                "borderStyle": "dashed"
            }
        },
        "type": "ImageBlock",
        "elementId": "LOGO",
        "url": "/images/DA (1).svg"
    },
    "primaryLinks": [
        {
            "label": "Pricing",
            "url": "/pricing",
            "icon": "arrowRight",
            "iconPosition": "right",
            "style": "secondary",
            "type": "Link"
        },
        {
            "label": "Blog",
            "altText": "Blog",
            "url": "/blog",
            "icon": "arrowRight",
            "iconPosition": "right",
            "style": "secondary",
            "type": "Link"
        },
        {
            "label": "Careers",
            "altText": "Careers page",
            "url": "/careers",
            "icon": "arrowRight",
            "iconPosition": "right",
            "style": "secondary",
            "type": "Link"
        },
        {
            "label": "Services",
            "altText": "Services",
            "links": [
                {
                    "label": "Dropdown item",
                    "url": "/",
                    "icon": "arrowRight",
                    "iconPosition": "right",
                    "style": "secondary",
                    "type": "Link"
                },
                {
                    "label": "Dropdown item",
                    "url": "/",
                    "icon": "arrowRight",
                    "iconPosition": "right",
                    "style": "secondary",
                    "type": "Link"
                },
                {
                    "label": "Dropdown item",
                    "url": "/",
                    "icon": "arrowRight",
                    "iconPosition": "right",
                    "style": "secondary",
                    "type": "Link"
                }
            ],
            "labelStyle": "secondary",
            "type": "SubNav"
        }
    ],
    "secondaryLinks": [
        {
            "label": "Contact us",
            "altText": "Contact us",
            "url": "/",
            "icon": "arrowRight",
            "iconPosition": "right",
            "style": "secondary",
            "type": "Button"
        },
        {
            "label": "Book Now",
            "url": "/",
            "icon": "arrowRight",
            "iconPosition": "right",
            "style": "primary",
            "type": "Button",
            "altText": "Book Now"
        }
    ],
    "variant": "logo-left-primary-nav-centered",
    "colors": "bg-light-fg-dark",
    "type": "Header"
}